[
  {
    "type": "noun",
    "es_word": "La carrera",
    "pl_word": "kierunek studiów",
    "examples": [
      {
        "es_form": "[La carrera::kierunek studiów] es muy exigente.",
        "pl_translation": "Kierunek studiów jest bardzo wymagający."
      },
      {
        "es_form": "Elegí [la carrera::kierunek studiów] de medicina.",
        "pl_translation": "Wybrałem kierunek studiów medycznych."
      },
      {
        "es_form": "Terminé [la carrera::kierunek studiów] el año pasado.",
        "pl_translation": "Ukończyłem kierunek studiów w zeszłym roku."
      }
    ]
  },
  {
    "type": "noun",
    "es_word": "La facultad",
    "pl_word": "wydział",
    "examples": [
      {
        "es_form": "Estudio en [la facultad::wydział] de derecho.",
        "pl_translation": "Studiuję na wydziale prawa."
      },
      {
        "es_form": "[La facultad::wydział] está en el centro.",
        "pl_translation": "Wydział jest w centrum."
      },
      {
        "es_form": "[La facultad::wydział] ofrece muchas carreras.",
        "pl_translation": "Wydział oferuje wiele kierunków."
      }
    ]
  },
  {
    "type": "noun",
    "es_word": "El título",
    "pl_word": "dyplom / tytuł",
    "examples": [
      {
        "es_form": "[El título::dyplom ] está sobre la mesa.",
        "pl_translation": "Dyplom jest na stole."
      },
      {
        "es_form": "Recibí [el título::dyplom ] la semana pasada.",
        "pl_translation": "Odebrałem dyplom w zeszłym tygodniu."
      },
      {
        "es_form": "Compré el marco para [el título::dyplom ] ayer.",
        "pl_translation": "Kupiłem ramkę na dyplom wczoraj."
      }
    ]
  },
  {
    "type": "noun",
    "es_word": "El máster",
    "pl_word": "magister",
    "examples": [
      {
        "es_form": "[El máster::magister] cuesta diez euros.",
        "pl_translation": "Magister kosztuje dziesięć euro."
      },
      {
        "es_form": "Terminé [el máster::magister] ayer.",
        "pl_translation": "Ukończyłem magistra wczoraj."
      },
      {
        "es_form": "[El máster::magister] dura dos años.",
        "pl_translation": "Magister trwa dwa lata."
      }
    ]
  },
  {
    "type": "noun",
    "es_word": "El doctorado",
    "pl_word": "doktorat",
    "examples": [
      {
        "es_form": "Estoy haciendo [el doctorado::doktorat] en química.",
        "pl_translation": "Robię doktorat z chemii."
      },
      {
        "es_form": "[El doctorado::doktorat] es un gran logro.",
        "pl_translation": "Doktorat to wielkie osiągnięcie."
      },
      {
        "es_form": "[El doctorado::doktorat] dura cuatro años.",
        "pl_translation": "Doktorat trwa cztery lata."
      }
    ]
  },
  {
    "type": "noun",
    "es_word": "La tesis",
    "pl_word": "praca dyplomowa",
    "examples": [
      {
        "es_form": "Estoy escribiendo [la tesis::praca dyplomowa].",
        "pl_translation": "Piszę pracę dyplomową."
      },
      {
        "es_form": "Defendí [la tesis::praca dyplomowa] ayer.",
        "pl_translation": "Obroniłem pracę dyplomową wczoraj."
      },
      {
        "es_form": "[La tesis::praca dyplomowa] es muy extensa.",
        "pl_translation": "Praca dyplomowa jest bardzo obszerna."
      }
    ]
  },
  {
    "type": "noun",
    "es_word": "El expediente",
    "pl_word": "indeks / świadectwo",
    "examples": [
      {
        "es_form": "Perdí [el expediente::indeks ].",
        "pl_translation": "Zgubiłem indeks."
      },
      {
        "es_form": "[El expediente::indeks ] cuesta diez euros.",
        "pl_translation": "Indeks kosztuje dziesięć euro."
      },
      {
        "es_form": "¿Has visto [el expediente::indeks ]?",
        "pl_translation": "Widziałeś mój indeks?"
      }
    ]
  },
  {
    "type": "noun",
    "es_word": "Los exámenes finales",
    "pl_word": "sesja egzaminacyjna",
    "examples": [
      {
        "es_form": "[Los exámenes finales::sesja egzaminacyjna] empiezan mañana.",
        "pl_translation": "Sesja egzaminacyjna zaczyna się jutro."
      },
      {
        "es_form": "¿Has aprobado [los exámenes finales::sesja egzaminacyjna]?",
        "pl_translation": "Czy zdałeś sesję egzaminacyjną?"
      },
      {
        "es_form": "Estoy estudiando para [los exámenes finales::sesja egzaminacyjna].",
        "pl_translation": "Uczę się do sesji egzaminacyjnej."
      }
    ]
  },
  {
    "type": "noun",
    "es_word": "La recuperación",
    "pl_word": "poprawka (egzamin)",
    "examples": [
      {
        "es_form": "Tengo [la recuperación::poprawka (egzamin)] el lunes.",
        "pl_translation": "Mam poprawkę w poniedziałek."
      },
      {
        "es_form": "Aprobé [la recuperación::poprawka (egzamin)].",
        "pl_translation": "Zdałem poprawkę."
      },
      {
        "es_form": "Estudio mucho para [la recuperación::poprawka (egzamin)].",
        "pl_translation": "Dużo się uczę do poprawki."
      }
    ]
  },
  {
    "type": "noun",
    "es_word": "El intercambio",
    "pl_word": "wymiana studencka",
    "examples": [
      {
        "es_form": "Participé en [el intercambio::wymiana studencka] el año pasado.",
        "pl_translation": "Wziąłem udział w wymianie studenckiej w zeszłym roku."
      },
      {
        "es_form": "[El intercambio::wymiana studencka] fue una experiencia increíble.",
        "pl_translation": "Wymiana studencka była niesamowitym doświadczeniem."
      },
      {
        "es_form": "Quiero solicitar [el intercambio::wymiana studencka].",
        "pl_translation": "Chcę ubiegać się o wymianę studencką."
      }
    ]
  },
  {
    "type": "adjective",
    "es_word": "académico",
    "pl_word": "akademicki",
    "examples": [
      {
        "es_form": "Nada es más importante que el rendimiento [académico::akademicki].",
        "pl_translation": "Nic nie jest ważniejsze niż wyniki akademickie."
      },
      {
        "es_form": "Es un artículo [académico::akademicki].",
        "pl_translation": "To jest artykuł akademicki."
      },
      {
        "es_form": "El año [académico::akademicki] empieza en octubre.",
        "pl_translation": "Rok akademicki zaczyna się w październiku."
      }
    ]
  },
  {
    "type": "adjective",
    "es_word": "culto",
    "pl_word": "wykształcony",
    "examples": [
      {
        "es_form": "Mi abuelo es una persona muy [culta::wykształcony].",
        "pl_translation": "Mój dziadek jest bardzo wykształconą osobą."
      },
      {
        "es_form": "Es una sociedad muy [culta::wykształcony].",
        "pl_translation": "To jest bardzo wykształcone społeczeństwo."
      },
      {
        "es_form": "Un hombre [culto::wykształcony] siempre sigue aprendiendo.",
        "pl_translation": "Wykształcony człowiek zawsze się uczy."
      }
    ]
  },
  {
    "type": "verb",
    "es_word": "estudiar",
    "pl_word": "studiować / uczyć się",
    "examples": [
      {
        "es_form": "Es importante [estudiar::studiować / uczyć się] todos los días.",
        "pl_translation": "Ważne jest uczyć się codziennie."
      },
      {
        "es_form": "Hay que [estudiar::studiować / uczyć się] con cuidado.",
        "pl_translation": "Trzeba uczyć się uważnie."
      },
      {
        "es_form": "Quiero [estudiar::studiować / uczyć się] ahora.",
        "pl_translation": "Chcę się teraz uczyć."
      }
    ],
    "forms": [
      {
        "es_word": "estudio",
        "pl_word": "studiuję",
        "grammar": {
          "tense": "present",
          "person": 1,
          "number": "singular"
        },
        "examples": [
          {
            "es_form": "[Estudio::studiuję] todos los días.",
            "pl_translation": "Studiuję codziennie."
          },
          {
            "es_form": "Siempre [estudio::studiuję] con atención.",
            "pl_translation": "Zawsze studiuję z uwagą."
          },
          {
            "es_form": "No [estudio::studiuję] muy bien últimamente.",
            "pl_translation": "Ostatnio nie studiuję zbyt dobrze."
          }
        ]
      },
      {
        "es_word": "estudias",
        "pl_word": "studiujesz",
        "grammar": {
          "tense": "present",
          "person": 2,
          "number": "singular"
        },
        "examples": [
          {
            "es_form": "Siempre [estudias::studiujesz] con atención.",
            "pl_translation": "Zawsze studiujesz z uwagą."
          },
          {
            "es_form": "[Estudias::studiujesz] todos los días.",
            "pl_translation": "Studiujesz codziennie."
          },
          {
            "es_form": "[Estudias::studiujesz] como me enseñaste.",
            "pl_translation": "Studiujesz tak jak mnie nauczyłeś."
          }
        ]
      },
      {
        "es_word": "estudia",
        "pl_word": "studiuje",
        "grammar": {
          "tense": "present",
          "person": 3,
          "number": "singular"
        },
        "examples": [
          {
            "es_form": "Siempre [estudia::studiuje] con atención.",
            "pl_translation": "Zawsze studiuje z uwagą."
          },
          {
            "es_form": "[Estudia::studiuje] como me enseñaste.",
            "pl_translation": "Studiuje tak jak mnie nauczyłeś."
          },
          {
            "es_form": "No [estudia::studiuje] muy bien últimamente.",
            "pl_translation": "Ostatnio nie studiuje zbyt dobrze."
          }
        ]
      },
      {
        "es_word": "estudiamos",
        "pl_word": "studiujemy",
        "grammar": {
          "tense": "present",
          "person": 1,
          "number": "plural"
        },
        "examples": [
          {
            "es_form": "[Estudiamos::studiujemy] como me enseñaste.",
            "pl_translation": "Studiujemy tak jak mnie nauczyłeś."
          },
          {
            "es_form": "Normalmente [estudiamos::studiujemy] por la mañana.",
            "pl_translation": "Zazwyczaj studiujemy rano."
          },
          {
            "es_form": "[Estudiamos::studiujemy] todos los días.",
            "pl_translation": "Studiujemy codziennie."
          }
        ]
      },
      {
        "es_word": "estudiáis",
        "pl_word": "studiujecie",
        "grammar": {
          "tense": "present",
          "person": 2,
          "number": "plural"
        },
        "examples": [
          {
            "es_form": "¿[Estudiáis::studiujecie] los fines de semana?",
            "pl_translation": "Czy studiujecie w weekendy?"
          },
          {
            "es_form": "[Estudiáis::studiujecie] como me enseñaste.",
            "pl_translation": "Studiujecie tak jak mnie nauczyłeś."
          },
          {
            "es_form": "No [estudiáis::studiujecie] muy bien últimamente.",
            "pl_translation": "Ostatnio nie studiujecie zbyt dobrze."
          }
        ]
      },
      {
        "es_word": "estudian",
        "pl_word": "studiują",
        "grammar": {
          "tense": "present",
          "person": 3,
          "number": "plural"
        },
        "examples": [
          {
            "es_form": "Normalmente [estudian::studiują] por la mañana.",
            "pl_translation": "Zazwyczaj studiują rano."
          },
          {
            "es_form": "[Estudian::studiują] como me enseñaste.",
            "pl_translation": "Studiują tak jak mnie nauczyłeś."
          },
          {
            "es_form": "Siempre [estudian::studiują] con atención.",
            "pl_translation": "Zawsze studiują z uwagą."
          }
        ]
      },
      {
        "es_word": "estudié",
        "pl_word": "studiowałem",
        "grammar": {
          "tense": "preterite",
          "person": 1,
          "number": "singular"
        },
        "examples": [
          {
            "es_form": "[Estudié::studiowałem] la semana pasada.",
            "pl_translation": "Studiowałem w zeszłym tygodniu."
          },
          {
            "es_form": "[Estudié::studiowałem] sin parar durante horas.",
            "pl_translation": "Studiowałem bez przerwy przez wiele godzin."
          },
          {
            "es_form": "Ayer [estudié::studiowałem] todo el día.",
            "pl_translation": "Wczoraj studiowałem cały dzień."
          }
        ]
      },
      {
        "es_word": "estudiaste",
        "pl_word": "studiowałeś",
        "grammar": {
          "tense": "preterite",
          "person": 2,
          "number": "singular"
        },
        "examples": [
          {
            "es_form": "Nunca [estudiaste::studiowałeś] algo así antes.",
            "pl_translation": "Nigdy wcześniej nie studiowałeś czegoś takiego."
          },
          {
            "es_form": "El mes pasado no [estudiaste::studiowałeś] nada.",
            "pl_translation": "W zeszłym miesiącu nic nie studiowałeś."
          },
          {
            "es_form": "¿[Estudiaste::studiowałeś] bien para el examen?",
            "pl_translation": "Czy dobrze studiowałeś do egzaminu?"
          }
        ]
      },
      {
        "es_word": "estudió",
        "pl_word": "studiował",
        "grammar": {
          "tense": "preterite",
          "person": 3,
          "number": "singular"
        },
        "examples": [
          {
            "es_form": "Nunca [estudió::studiował] algo así antes.",
            "pl_translation": "Nigdy wcześniej nie studiował czegoś takiego."
          },
          {
            "es_form": "¿[Estudió::studiował] bien para el examen?",
            "pl_translation": "Czy dobrze studiował do egzaminu?"
          },
          {
            "es_form": "[Estudió::studiował] sin parar durante horas.",
            "pl_translation": "Studiował bez przerwy przez wiele godzin."
          }
        ]
      },
      {
        "es_word": "estudiamos",
        "pl_word": "studiowaliśmy",
        "grammar": {
          "tense": "preterite",
          "person": 1,
          "number": "plural"
        },
        "examples": [
          {
            "es_form": "¿[Estudiamos::studiowaliśmy] bien para el examen?",
            "pl_translation": "Czy dobrze studiowaliśmy do egzaminu?"
          },
          {
            "es_form": "[Estudiamos::studiowaliśmy] la semana pasada.",
            "pl_translation": "Studiowaliśmy w zeszłym tygodniu."
          },
          {
            "es_form": "El mes pasado no [estudiamos::studiowaliśmy] nada.",
            "pl_translation": "W zeszłym miesiącu nic nie studiowaliśmy."
          }
        ]
      },
      {
        "es_word": "estudiasteis",
        "pl_word": "studiowaliście",
        "grammar": {
          "tense": "preterite",
          "person": 2,
          "number": "plural"
        },
        "examples": [
          {
            "es_form": "Ayer [estudiasteis::studiowaliście] todo el día.",
            "pl_translation": "Wczoraj studiowaliście cały dzień."
          },
          {
            "es_form": "El mes pasado no [estudiasteis::studiowaliście] nada.",
            "pl_translation": "W zeszłym miesiącu nic nie studiowaliście."
          },
          {
            "es_form": "Nunca [estudiasteis::studiowaliście] algo así antes.",
            "pl_translation": "Nigdy wcześniej nie studiowaliście czegoś takiego."
          }
        ]
      },
      {
        "es_word": "estudiaron",
        "pl_word": "studiowali",
        "grammar": {
          "tense": "preterite",
          "person": 3,
          "number": "plural"
        },
        "examples": [
          {
            "es_form": "[Estudiaron::studiowali] sin parar durante horas.",
            "pl_translation": "Studiowali bez przerwy przez wiele godzin."
          },
          {
            "es_form": "[Estudiaron::studiowali] la semana pasada.",
            "pl_translation": "Studiowali w zeszłym tygodniu."
          },
          {
            "es_form": "Nunca [estudiaron::studiowali] algo así antes.",
            "pl_translation": "Nigdy wcześniej nie studiowali czegoś takiego."
          }
        ]
      },
      {
        "es_word": "estudiaré",
        "pl_word": "będę studiować",
        "grammar": {
          "tense": "future",
          "person": 1,
          "number": "singular"
        },
        "examples": [
          {
            "es_form": "Mañana [estudiaré::będę studiować] más temprano.",
            "pl_translation": "Jutro będę studiować wcześniej."
          },
          {
            "es_form": "¿[Estudiaré::będę studiować] con nosotros mañana?",
            "pl_translation": "Czy będę studiować z nami jutro?"
          },
          {
            "es_form": "El año que viene [estudiaré::będę studiować] en España.",
            "pl_translation": "W przyszłym roku będę studiować w Hiszpanii."
          }
        ]
      },
      {
        "es_word": "estudiarás",
        "pl_word": "będziesz studiować",
        "grammar": {
          "tense": "future",
          "person": 2,
          "number": "singular"
        },
        "examples": [
          {
            "es_form": "[Estudiarás::będziesz studiować] la próxima semana.",
            "pl_translation": "Będziesz studiować w przyszłym tygodniu."
          },
          {
            "es_form": "El año que viene [estudiarás::będziesz studiować] en España.",
            "pl_translation": "W przyszłym roku będziesz studiować w Hiszpanii."
          },
          {
            "es_form": "Creo que [estudiarás::będziesz studiować] bien.",
            "pl_translation": "Myślę, że będziesz dobrze studiować."
          }
        ]
      },
      {
        "es_word": "estudiará",
        "pl_word": "będzie studiować",
        "grammar": {
          "tense": "future",
          "person": 3,
          "number": "singular"
        },
        "examples": [
          {
            "es_form": "¿[Estudiará::będzie studiować] con nosotros mañana?",
            "pl_translation": "Czy będzie studiować z nami jutro?"
          },
          {
            "es_form": "Te prometo que [estudiará::będzie studiować] a tiempo.",
            "pl_translation": "Obiecuję ci, że będzie studiować na czas."
          },
          {
            "es_form": "Mañana [estudiará::będzie studiować] más temprano.",
            "pl_translation": "Jutro będzie studiować wcześniej."
          }
        ]
      },
      {
        "es_word": "estudiaremos",
        "pl_word": "będziemy studiować",
        "grammar": {
          "tense": "future",
          "person": 1,
          "number": "plural"
        },
        "examples": [
          {
            "es_form": "El año que viene [estudiaremos::będziemy studiować] en España.",
            "pl_translation": "W przyszłym roku będziemy studiować w Hiszpanii."
          },
          {
            "es_form": "Mañana [estudiaremos::będziemy studiować] más temprano.",
            "pl_translation": "Jutro będziemy studiować wcześniej."
          },
          {
            "es_form": "¿[Estudiaremos::będziemy studiować] con nosotros mañana?",
            "pl_translation": "Czy będziemy studiować z nami jutro?"
          }
        ]
      },
      {
        "es_word": "estudiaréis",
        "pl_word": "będziecie studiować",
        "grammar": {
          "tense": "future",
          "person": 2,
          "number": "plural"
        },
        "examples": [
          {
            "es_form": "¿[Estudiaréis::będziecie studiować] con nosotros mañana?",
            "pl_translation": "Czy będziecie studiować z nami jutro?"
          },
          {
            "es_form": "[Estudiaréis::będziecie studiować] la próxima semana.",
            "pl_translation": "Będziecie studiować w przyszłym tygodniu."
          },
          {
            "es_form": "Creo que [estudiaréis::będziecie studiować] bien.",
            "pl_translation": "Myślę, że będziecie dobrze studiować."
          }
        ]
      },
      {
        "es_word": "estudiarán",
        "pl_word": "będą studiować",
        "grammar": {
          "tense": "future",
          "person": 3,
          "number": "plural"
        },
        "examples": [
          {
            "es_form": "Creo que [estudiarán::będą studiować] bien.",
            "pl_translation": "Myślę, że będą dobrze studiować."
          },
          {
            "es_form": "El año que viene [estudiarán::będą studiować] en España.",
            "pl_translation": "W przyszłym roku będą studiować w Hiszpanii."
          },
          {
            "es_form": "Te prometo que [estudiarán::będą studiować] a tiempo.",
            "pl_translation": "Obiecuję ci, że będą studiować na czas."
          }
        ]
      }
    ]
  }
]