[
  {
    "type": "noun",
    "es_word": "La duda",
    "pl_word": "wątpliwość",
    "examples": [
      {
        "es_form": "[La duda::wątpliwość] está sobre la mesa.",
        "pl_translation": "Wątpliwość jest na stole."
      },
      {
        "es_form": "[La duda::wątpliwość] cuesta diez euros.",
        "pl_translation": "Wątpliwość kosztuje dziesięć euro."
      },
      {
        "es_form": "Se me rompio [la duda::wątpliwość].",
        "pl_translation": "Zepsuł mi się wątpliwość."
      }
    ]
  },
  {
    "type": "noun",
    "es_word": "La curiosidad",
    "pl_word": "ciekawość",
    "examples": [
      {
        "es_form": "¿Has visto [la curiosidad::ciekawość]?",
        "pl_translation": "Widziałeś"
      },
      {
        "es_form": "Se me rompio [la curiosidad::ciekawość].",
        "pl_translation": "Zepsuł mi się ciekawość."
      },
      {
        "es_form": "[La curiosidad::ciekawość] está sobre la mesa.",
        "pl_translation": "Ciekawość jest na stole."
      }
    ]
  },
  {
    "type": "noun",
    "es_word": "La entrevista",
    "pl_word": "wywiad, rozmowa",
    "examples": [
      {
        "es_form": "Se me rompio [la entrevista::wywiad, rozmowa].",
        "pl_translation": "Zepsuł mi się wywiad, rozmowa."
      },
      {
        "es_form": "[La entrevista::wywiad, rozmowa] cuesta diez euros.",
        "pl_translation": "Wywiad, rozmowa kosztuje dziesięć euro."
      },
      {
        "es_form": "[La entrevista::wywiad, rozmowa] está sobre la mesa.",
        "pl_translation": "Wywiad, rozmowa jest na stole."
      }
    ]
  },
  {
    "type": "noun",
    "es_word": "La encuesta",
    "pl_word": "ankieta",
    "examples": [
      {
        "es_form": "Guarda [la encuesta::ankieta] en el armario.",
        "pl_translation": "Schowaj ankieta do szafy."
      },
      {
        "es_form": "Compré [la encuesta::ankieta] ayer.",
        "pl_translation": "Kupiłem"
      },
      {
        "es_form": "Necesito [la encuesta::ankieta] nuevo.",
        "pl_translation": "Potrzebuję nowy"
      }
    ]
  },
  {
    "type": "noun",
    "es_word": "El opinión",
    "pl_word": "opinia",
    "examples": [
      {
        "es_form": "[El opinión::opinia] cuesta diez euros.",
        "pl_translation": "Opinia kosztuje dziesięć euro."
      },
      {
        "es_form": "[El opinión::opinia] es de madera.",
        "pl_translation": "Opinia jest z drewna."
      },
      {
        "es_form": "Se me rompio [el opinión::opinia].",
        "pl_translation": "Zepsuł mi się opinia."
      }
    ]
  },
  {
    "type": "noun",
    "es_word": "El consejo",
    "pl_word": "rada",
    "examples": [
      {
        "es_form": "[El consejo::rada] está sobre la mesa.",
        "pl_translation": "Rada jest na stole."
      },
      {
        "es_form": "[El consejo::rada] es de madera.",
        "pl_translation": "Rada jest z drewna."
      },
      {
        "es_form": "Guarda [el consejo::rada] en el armario.",
        "pl_translation": "Schowaj rada do szafy."
      }
    ]
  },
  {
    "type": "noun",
    "es_word": "El explicación",
    "pl_word": "wyjaśnienie",
    "examples": [
      {
        "es_form": "[El explicación::wyjaśnienie] está sobre la mesa.",
        "pl_translation": "Wyjaśnienie jest na stole."
      },
      {
        "es_form": "Se me rompio [el explicación::wyjaśnienie].",
        "pl_translation": "Zepsuł mi się wyjaśnienie."
      },
      {
        "es_form": "[El explicación::wyjaśnienie] cuesta diez euros.",
        "pl_translation": "Wyjaśnienie kosztuje dziesięć euro."
      }
    ]
  },
  {
    "type": "noun",
    "es_word": "El detalle",
    "pl_word": "szczegół",
    "examples": [
      {
        "es_form": "Compré [el detalle::szczegół] ayer.",
        "pl_translation": "Kupiłem"
      },
      {
        "es_form": "[El detalle::szczegół] cuesta diez euros.",
        "pl_translation": "Szczegół kosztuje dziesięć euro."
      },
      {
        "es_form": "Guarda [el detalle::szczegół] en el armario.",
        "pl_translation": "Schowaj szczegół do szafy."
      }
    ]
  },
  {
    "type": "noun",
    "es_word": "El tema",
    "pl_word": "temat",
    "examples": [
      {
        "es_form": "Tienes que aceptar [el tema::temat].",
        "pl_translation": "Musisz zaakceptować temat."
      },
      {
        "es_form": "[El tema::temat] es la clave del éxito.",
        "pl_translation": "Temat jest kluczem do sukcesu."
      },
      {
        "es_form": "No entiendo [el tema::temat].",
        "pl_translation": "Nie rozumiem temat."
      }
    ]
  },
  {
    "type": "noun",
    "es_word": "El solución",
    "pl_word": "rozwiązanie",
    "examples": [
      {
        "es_form": "[El solución::rozwiązanie] es la clave del éxito.",
        "pl_translation": "Rozwiązanie jest kluczem do sukcesu."
      },
      {
        "es_form": "No entiendo [el solución::rozwiązanie].",
        "pl_translation": "Nie rozumiem rozwiązanie."
      },
      {
        "es_form": "Hablamos sobre [el solución::rozwiązanie].",
        "pl_translation": "Rozmawialiśmy o rozwiązanie."
      }
    ]
  },
  {
    "type": "adjective",
    "es_word": "curioso",
    "pl_word": "ciekawy, ciekawski",
    "examples": [
      {
        "es_form": "Nada es más [curioso::ciekawy, ciekawski] que la familia.",
        "pl_translation": "Nic nie jest ciekawy, ciekawski od rodziny."
      },
      {
        "es_form": "La comida está [curiosa::ciekawy, ciekawski].",
        "pl_translation": "Jedzenie jest ciekawy, ciekawski."
      },
      {
        "es_form": "Este coche es [curioso::ciekawy, ciekawski].",
        "pl_translation": "Ten samochód jest ciekawy, ciekawski."
      }
    ]
  },
  {
    "type": "adjective",
    "es_word": "claro",
    "pl_word": "jasny, zrozumiały",
    "examples": [
      {
        "es_form": "La comida está [clara::jasny, zrozumiały].",
        "pl_translation": "Jedzenie jest jasny, zrozumiały."
      },
      {
        "es_form": "Se compro un vestido [claro::jasny, zrozumiały].",
        "pl_translation": "Kupiła sobie jasny, zrozumiały sukienkę."
      },
      {
        "es_form": "Este coche es [claro::jasny, zrozumiały].",
        "pl_translation": "Ten samochód jest jasny, zrozumiały."
      }
    ]
  },
  {
    "type": "verb",
    "es_word": "preguntar",
    "pl_word": "pytać (zadawać pytanie)",
    "examples": [
      {
        "es_form": "Hay que [preguntar::pytać (zadawać pytanie)] con cuidado.",
        "pl_translation": "Trzeba pytać ostrożnie."
      },
      {
        "es_form": "Quiero [preguntar::pytać (zadawać pytanie)] ahora.",
        "pl_translation": "Chcę pytać teraz."
      },
      {
        "es_form": "Me gusta [preguntar::pytać (zadawać pytanie)] por la mañana.",
        "pl_translation": "Lubię pytać rano."
      }
    ],
    "forms": [
      {
        "es_word": "pregunto",
        "pl_word": "pytam",
        "grammar": {
          "tense": "present",
          "person": 1,
          "number": "singular"
        },
        "examples": [
          {
            "es_form": "¿[pregunto::pytam] los fines de semana?",
            "pl_translation": "Czy pytam w weekendy?"
          },
          {
            "es_form": "Siempre [pregunto::pytam] con atencion.",
            "pl_translation": "Zawsze pytam z uwagą."
          },
          {
            "es_form": "[pregunto::pytam] todos los días.",
            "pl_translation": "Pytam codziennie."
          }
        ]
      },
      {
        "es_word": "preguntas",
        "pl_word": "pytasz",
        "grammar": {
          "tense": "present",
          "person": 2,
          "number": "singular"
        },
        "examples": [
          {
            "es_form": "[preguntas::pytasz] todos los días.",
            "pl_translation": "Pytasz codziennie."
          },
          {
            "es_form": "¿[preguntas::pytasz] los fines de semana?",
            "pl_translation": "Czy pytasz w weekendy?"
          },
          {
            "es_form": "Siempre [preguntas::pytasz] con atencion.",
            "pl_translation": "Zawsze pytasz z uwagą."
          }
        ]
      },
      {
        "es_word": "pregunta",
        "pl_word": "pyta",
        "grammar": {
          "tense": "present",
          "person": 3,
          "number": "singular"
        },
        "examples": [
          {
            "es_form": "Normalmente [pregunta::pyta] por la mañana.",
            "pl_translation": "Zazwyczaj pytać rano."
          },
          {
            "es_form": "Siempre [pregunta::pyta] con atencion.",
            "pl_translation": "Zawsze pytać z uwagą."
          },
          {
            "es_form": "No [pregunta::pyta] muy bien últimamente.",
            "pl_translation": "Ostatnio nie pytać zbyt dobrze."
          }
        ]
      },
      {
        "es_word": "preguntamos",
        "pl_word": "pytamy",
        "grammar": {
          "tense": "present",
          "person": 1,
          "number": "plural"
        },
        "examples": [
          {
            "es_form": "[preguntamos::pytamy] como me enseñaste.",
            "pl_translation": "Pytamy tak jak mnie nauczyłeś"
          },
          {
            "es_form": "[preguntamos::pytamy] todos los días.",
            "pl_translation": "Pytamy codziennie."
          },
          {
            "es_form": "Normalmente [preguntamos::pytamy] por la mañana.",
            "pl_translation": "Zazwyczaj pytamy rano."
          }
        ]
      },
      {
        "es_word": "preguntáis",
        "pl_word": "pytacie",
        "grammar": {
          "tense": "present",
          "person": 2,
          "number": "plural"
        },
        "examples": [
          {
            "es_form": "[preguntáis::pytacie] todos los días.",
            "pl_translation": "Pytacie codziennie."
          },
          {
            "es_form": "Siempre [preguntáis::pytacie] con atencion.",
            "pl_translation": "Zawsze pytacie z uwagą."
          },
          {
            "es_form": "¿[preguntáis::pytacie] los fines de semana?",
            "pl_translation": "Czy pytacie w weekendy?"
          }
        ]
      },
      {
        "es_word": "preguntan",
        "pl_word": "pytają",
        "grammar": {
          "tense": "present",
          "person": 3,
          "number": "plural"
        },
        "examples": [
          {
            "es_form": "Normalmente [preguntan::pytają] por la mañana.",
            "pl_translation": "Zazwyczaj pytają rano."
          },
          {
            "es_form": "[preguntan::pytają] como me enseñaste.",
            "pl_translation": "Pytają tak jak mnie nauczyłeś"
          },
          {
            "es_form": "¿[preguntan::pytają] los fines de semana?",
            "pl_translation": "Czy pytają w weekendy?"
          }
        ]
      },
      {
        "es_word": "pregunté",
        "pl_word": "pytałem",
        "grammar": {
          "tense": "preterite",
          "person": 1,
          "number": "singular"
        },
        "examples": [
          {
            "es_form": "Nunca [pregunté::pytałem] algo así antes.",
            "pl_translation": "Nigdy wcześniej nie pytałem czegoś takiego."
          },
          {
            "es_form": "El mes pasado no [pregunté::pytałem] nada.",
            "pl_translation": "W zeszłym miesiącu nic nie pytałem."
          },
          {
            "es_form": "¿[pregunté::pytałem] bien el examen?",
            "pl_translation": "Czy pytałem dobrze egzamin?"
          }
        ]
      },
      {
        "es_word": "preguntaste",
        "pl_word": "pytałeś",
        "grammar": {
          "tense": "preterite",
          "person": 2,
          "number": "singular"
        },
        "examples": [
          {
            "es_form": "[preguntaste::pytałeś] sin parar durante horas.",
            "pl_translation": "Pytałeś bez przerwy przez wiele godzin."
          },
          {
            "es_form": "El mes pasado no [preguntaste::pytałeś] nada.",
            "pl_translation": "W zeszłym miesiącu nic nie pytałeś."
          },
          {
            "es_form": "Ayer [preguntaste::pytałeś] todo el día.",
            "pl_translation": "Wczoraj pytałeś cały dzień."
          }
        ]
      },
      {
        "es_word": "preguntó",
        "pl_word": "pytał",
        "grammar": {
          "tense": "preterite",
          "person": 3,
          "number": "singular"
        },
        "examples": [
          {
            "es_form": "Nunca [preguntó::pytał] algo así antes.",
            "pl_translation": "Nigdy wcześniej nie pytał czegoś takiego."
          },
          {
            "es_form": "El mes pasado no [preguntó::pytał] nada.",
            "pl_translation": "W zeszłym miesiącu nic nie pytał."
          },
          {
            "es_form": "[preguntó::pytał] sin parar durante horas.",
            "pl_translation": "Pytał bez przerwy przez wiele godzin."
          }
        ]
      },
      {
        "es_word": "preguntamos",
        "pl_word": "pytaliśmy",
        "grammar": {
          "tense": "preterite",
          "person": 1,
          "number": "plural"
        },
        "examples": [
          {
            "es_form": "[preguntamos::pytaliśmy] la semana pasada.",
            "pl_translation": "Pytaliśmy w zeszłym tygodniu."
          },
          {
            "es_form": "[preguntamos::pytaliśmy] sin parar durante horas.",
            "pl_translation": "Pytaliśmy bez przerwy przez wiele godzin."
          },
          {
            "es_form": "Ayer [preguntamos::pytaliśmy] todo el día.",
            "pl_translation": "Wczoraj pytaliśmy cały dzień."
          }
        ]
      },
      {
        "es_word": "preguntasteis",
        "pl_word": "pytaliście",
        "grammar": {
          "tense": "preterite",
          "person": 2,
          "number": "plural"
        },
        "examples": [
          {
            "es_form": "[preguntasteis::pytaliście] sin parar durante horas.",
            "pl_translation": "Pytaliście bez przerwy przez wiele godzin."
          },
          {
            "es_form": "[preguntasteis::pytaliście] la semana pasada.",
            "pl_translation": "Pytaliście w zeszłym tygodniu."
          },
          {
            "es_form": "¿[preguntasteis::pytaliście] bien el examen?",
            "pl_translation": "Czy pytaliście dobrze egzamin?"
          }
        ]
      },
      {
        "es_word": "preguntaron",
        "pl_word": "pytali",
        "grammar": {
          "tense": "preterite",
          "person": 3,
          "number": "plural"
        },
        "examples": [
          {
            "es_form": "[preguntaron::pytali] sin parar durante horas.",
            "pl_translation": "Pytali bez przerwy przez wiele godzin."
          },
          {
            "es_form": "¿[preguntaron::pytali] bien el examen?",
            "pl_translation": "Czy pytali dobrze egzamin?"
          },
          {
            "es_form": "Ayer [preguntaron::pytali] todo el día.",
            "pl_translation": "Wczoraj pytali cały dzień."
          }
        ]
      },
      {
        "es_word": "pregunté",
        "pl_word": "będę pytać",
        "grammar": {
          "tense": "future",
          "person": 1,
          "number": "singular"
        },
        "examples": [
          {
            "es_form": "El año que viene [pregunté::będę pytać] en España.",
            "pl_translation": "W przyszłym roku będę pytać w Hiszpanii."
          },
          {
            "es_form": "[pregunté::będę pytać] la proxima semana.",
            "pl_translation": "Będę pytać w przyszłym tygodniu."
          },
          {
            "es_form": "Te prometo que [pregunté::będę pytać] a tiempo.",
            "pl_translation": "Obiecuję ci, że będę pytać na czas."
          }
        ]
      },
      {
        "es_word": "preguntás",
        "pl_word": "będziesz pytać",
        "grammar": {
          "tense": "future",
          "person": 2,
          "number": "singular"
        },
        "examples": [
          {
            "es_form": "El año que viene [preguntás::będziesz pytać] en España.",
            "pl_translation": "W przyszłym roku będziesz pytać w Hiszpanii."
          },
          {
            "es_form": "[preguntás::będziesz pytać] la proxima semana.",
            "pl_translation": "Będziesz pytać w przyszłym tygodniu."
          },
          {
            "es_form": "¿[preguntás::będziesz pytać] con nosotros mañana?",
            "pl_translation": "Czy będziesz pytać z nami jutro?"
          }
        ]
      },
      {
        "es_word": "preguntá",
        "pl_word": "będzie pytać",
        "grammar": {
          "tense": "future",
          "person": 3,
          "number": "singular"
        },
        "examples": [
          {
            "es_form": "¿[preguntá::będzie pytać] con nosotros mañana?",
            "pl_translation": "Czy będzie pytać z nami jutro?"
          },
          {
            "es_form": "Creo que [preguntá::będzie pytać] bien.",
            "pl_translation": "Myślę, że będzie pytać dobrze."
          },
          {
            "es_form": "Te prometo que [preguntá::będzie pytać] a tiempo.",
            "pl_translation": "Obiecuję ci, że będzie pytać na czas."
          }
        ]
      },
      {
        "es_word": "preguntemos",
        "pl_word": "będziemy pytać",
        "grammar": {
          "tense": "future",
          "person": 1,
          "number": "plural"
        },
        "examples": [
          {
            "es_form": "Mañana [preguntemos::będziemy pytać] más temprano.",
            "pl_translation": "Jutro będziemy pytać wcześniej."
          },
          {
            "es_form": "Te prometo que [preguntemos::będziemy pytać] a tiempo.",
            "pl_translation": "Obiecuję ci, że będziemy pytać na czas."
          },
          {
            "es_form": "El año que viene [preguntemos::będziemy pytać] en España.",
            "pl_translation": "W przyszłym roku będziemy pytać w Hiszpanii."
          }
        ]
      },
      {
        "es_word": "preguntéis",
        "pl_word": "będziecie pytać",
        "grammar": {
          "tense": "future",
          "person": 2,
          "number": "plural"
        },
        "examples": [
          {
            "es_form": "Creo que [preguntéis::będziecie pytać] bien.",
            "pl_translation": "Myślę, że będziecie pytać dobrze."
          },
          {
            "es_form": "[preguntéis::będziecie pytać] la proxima semana.",
            "pl_translation": "Będziecie pytać w przyszłym tygodniu."
          },
          {
            "es_form": "Te prometo que [preguntéis::będziecie pytać] a tiempo.",
            "pl_translation": "Obiecuję ci, że będziecie pytać na czas."
          }
        ]
      },
      {
        "es_word": "preguntán",
        "pl_word": "będą pytać",
        "grammar": {
          "tense": "future",
          "person": 3,
          "number": "plural"
        },
        "examples": [
          {
            "es_form": "¿[preguntán::będą pytać] con nosotros mañana?",
            "pl_translation": "Czy będą pytać z nami jutro?"
          },
          {
            "es_form": "[preguntán::będą pytać] la proxima semana.",
            "pl_translation": "Będą pytać w przyszłym tygodniu."
          },
          {
            "es_form": "Mañana [preguntán::będą pytać] más temprano.",
            "pl_translation": "Jutro będą pytać wcześniej."
          }
        ]
      }
    ]
  }
]