[
  {
    "type": "noun",
    "es_word": "El río",
    "pl_word": "rzeka",
    "examples": [
      {
        "es_form": "Este es [el río::rzeka].",
        "pl_translation": "To jest rzeka."
      },
      {
        "es_form": "¿Dónde está [el río::rzeka]?",
        "pl_translation": "Gdzie jest rzeka?"
      },
      {
        "es_form": "[El río::rzeka] abre a las ocho.",
        "pl_translation": "Rzeka otwiera się o ósmej."
      }
    ]
  },
  {
    "type": "noun",
    "es_word": "El lago",
    "pl_word": "jezioro",
    "examples": [
      {
        "es_form": "Este es [el lago::jezioro].",
        "pl_translation": "To jest jezioro."
      },
      {
        "es_form": "¿Dónde está [el lago::jezioro]?",
        "pl_translation": "Gdzie jest jezioro?"
      },
      {
        "es_form": "[El lago::jezioro] está aquí.",
        "pl_translation": "Jezioro jest tutaj."
      }
    ]
  },
  {
    "type": "noun",
    "es_word": "La isla",
    "pl_word": "wyspa",
    "examples": [
      {
        "es_form": "Esta es [la isla::wyspa].",
        "pl_translation": "To jest wyspa."
      },
      {
        "es_form": "¿Dónde está [la isla::wyspa]?",
        "pl_translation": "Gdzie jest wyspa?"
      },
      {
        "es_form": "[La isla::wyspa] está cerca de aquí.",
        "pl_translation": "Wyspa jest niedaleko stąd."
      }
    ]
  },
  {
    "type": "noun",
    "es_word": "El desierto",
    "pl_word": "pustynia",
    "examples": [
      {
        "es_form": "Este es [el desierto::pustynia].",
        "pl_translation": "To jest pustynia."
      },
      {
        "es_form": "¿Dónde está [el desierto::pustynia]?",
        "pl_translation": "Gdzie jest pustynia?"
      },
      {
        "es_form": "[El desierto::pustynia] está aquí.",
        "pl_translation": "Pustynia jest tutaj."
      }
    ]
  },
  {
    "type": "noun",
    "es_word": "La colina",
    "pl_word": "wzgórze",
    "examples": [
      {
        "es_form": "Esta es [la colina::wzgórze].",
        "pl_translation": "To jest wzgórze."
      },
      {
        "es_form": "¿Dónde está [la colina::wzgórze]?",
        "pl_translation": "Gdzie jest wzgórze?"
      },
      {
        "es_form": "No es [la colina::wzgórze].",
        "pl_translation": "To nie jest wzgórze."
      }
    ]
  },
  {
    "type": "noun",
    "es_word": "La roca",
    "pl_word": "skała",
    "examples": [
      {
        "es_form": "Esta es [la roca::skała].",
        "pl_translation": "To jest skała."
      },
      {
        "es_form": "¿Dónde está [la roca::skała]?",
        "pl_translation": "Gdzie jest skała?"
      },
      {
        "es_form": "No es [la roca::skała].",
        "pl_translation": "To nie jest skała."
      }
    ]
  },
  {
    "type": "noun",
    "es_word": "El aire",
    "pl_word": "powietrze",
    "examples": [
      {
        "es_form": "¿Dónde está [el aire::powietrze]?",
        "pl_translation": "Gdzie jest powietrze?"
      },
      {
        "es_form": "[El aire::powietrze] está aquí.",
        "pl_translation": "Powietrze jest tutaj."
      },
      {
        "es_form": "Este es [el aire::powietrze].",
        "pl_translation": "To jest powietrze."
      }
    ]
  },
  {
    "type": "noun",
    "es_word": "El medio ambiente",
    "pl_word": "środowisko",
    "examples": [
      {
        "es_form": "Este es [el medio ambiente::środowisko].",
        "pl_translation": "To jest środowisko."
      },
      {
        "es_form": "¿Dónde está [el medio ambiente::środowisko]?",
        "pl_translation": "Gdzie jest środowisko?"
      },
      {
        "es_form": "No es [el medio ambiente::środowisko].",
        "pl_translation": "To nie jest środowisko."
      }
    ]
  },
  {
    "type": "noun",
    "es_word": "La contaminación",
    "pl_word": "zanieczyszczenie",
    "examples": [
      {
        "es_form": "Esta es [la contaminación::zanieczyszczenie].",
        "pl_translation": "To jest zanieczyszczenie."
      },
      {
        "es_form": "No es [la contaminación::zanieczyszczenie].",
        "pl_translation": "To nie jest zanieczyszczenie."
      },
      {
        "es_form": "Hablamos sobre [la contaminación::zanieczyszczenie].",
        "pl_translation": "Rozmawiamy o tym, czym jest zanieczyszczenie."
      }
    ]
  },
  {
    "type": "noun",
    "es_word": "La naturaleza",
    "pl_word": "natura, przyroda",
    "examples": [
      {
        "es_form": "Esta es [la naturaleza::natura].",
        "pl_translation": "To jest natura."
      },
      {
        "es_form": "No es [la naturaleza::natura].",
        "pl_translation": "To nie jest natura."
      },
      {
        "es_form": "¿Dónde está [la naturaleza::natura]?",
        "pl_translation": "Gdzie jest natura?"
      }
    ]
  },
  {
    "type": "adjective",
    "es_word": "natural",
    "pl_word": "naturalny",
    "examples": [
      {
        "es_form": "No es [natural::naturalny].",
        "pl_translation": "Nie jest naturalny."
      },
      {
        "es_form": "Parece [natural::naturalny].",
        "pl_translation": "Wydaje się naturalny."
      },
      {
        "es_form": "Es demasiado [natural::naturalny].",
        "pl_translation": "Jest zbyt naturalny."
      }
    ]
  },
  {
    "type": "adjective",
    "es_word": "puro",
    "pl_word": "czysty (środowisko)",
    "examples": [
      {
        "es_form": "No es [puro::czysty].",
        "pl_translation": "Nie jest czysty."
      },
      {
        "es_form": "Parece [puro::czysty].",
        "pl_translation": "Wydaje się czysty."
      },
      {
        "es_form": "Es demasiado [puro::czysty].",
        "pl_translation": "Jest zbyt czysty."
      }
    ]
  },
  {
    "type": "verb",
    "es_word": "proteger",
    "pl_word": "chronić",
    "examples": [
      {
        "es_form": "Quiero [proteger::chronić] a la familia.",
        "pl_translation": "Chcę chronić rodzinę."
      },
      {
        "es_form": "No puedo [proteger::chronić] a la familia hoy.",
        "pl_translation": "Nie mogę dziś chronić rodzinę."
      }
    ],
    "forms": [
      {
        "es_word": "protejo",
        "pl_word": "chronię (proteger)",
        "grammar": {
          "tense": "present",
          "person": 1,
          "number": "singular"
        },
        "examples": [
          {
            "es_form": "Yo [protejo::chronię] a la familia.",
            "pl_translation": "Chronię rodzinę."
          }
        ]
      },
      {
        "es_word": "proteges",
        "pl_word": "chronisz (proteger)",
        "grammar": {
          "tense": "present",
          "person": 2,
          "number": "singular"
        },
        "examples": [
          {
            "es_form": "Tú [proteges::chronisz] a la familia.",
            "pl_translation": "Chronisz rodzinę."
          }
        ]
      },
      {
        "es_word": "protege",
        "pl_word": "chroni (proteger)",
        "grammar": {
          "tense": "present",
          "person": 3,
          "number": "singular"
        },
        "examples": [
          {
            "es_form": "Él [protege::chroni] a la familia.",
            "pl_translation": "Chroni rodzinę."
          }
        ]
      },
      {
        "es_word": "protegemos",
        "pl_word": "chronimy (proteger)",
        "grammar": {
          "tense": "present",
          "person": 1,
          "number": "plural"
        },
        "examples": [
          {
            "es_form": "Nosotros [protegemos::chronimy] a la familia.",
            "pl_translation": "Chronimy rodzinę."
          }
        ]
      },
      {
        "es_word": "protegéis",
        "pl_word": "chronicie (proteger)",
        "grammar": {
          "tense": "present",
          "person": 2,
          "number": "plural"
        },
        "examples": [
          {
            "es_form": "Vosotros [protegéis::chronicie] a la familia.",
            "pl_translation": "Chronicie rodzinę."
          }
        ]
      },
      {
        "es_word": "protegen",
        "pl_word": "chronią (proteger)",
        "grammar": {
          "tense": "present",
          "person": 3,
          "number": "plural"
        },
        "examples": [
          {
            "es_form": "Ellos [protegen::chronią] a la familia.",
            "pl_translation": "Chronią rodzinę."
          }
        ]
      },
      {
        "es_word": "protegí",
        "pl_word": "ochroniłem (proteger)",
        "grammar": {
          "tense": "preterite",
          "person": 1,
          "number": "singular"
        },
        "examples": [
          {
            "es_form": "Yo [protegí::ochroniłem] a la familia.",
            "pl_translation": "Ochroniłem rodzinę."
          }
        ]
      },
      {
        "es_word": "protegiste",
        "pl_word": "ochroniłeś (proteger)",
        "grammar": {
          "tense": "preterite",
          "person": 2,
          "number": "singular"
        },
        "examples": [
          {
            "es_form": "Tú [protegiste::ochroniłeś] a la familia.",
            "pl_translation": "Ochroniłeś rodzinę."
          }
        ]
      },
      {
        "es_word": "protegió",
        "pl_word": "ochronił (proteger)",
        "grammar": {
          "tense": "preterite",
          "person": 3,
          "number": "singular"
        },
        "examples": [
          {
            "es_form": "Él [protegió::ochronił] a la familia.",
            "pl_translation": "Ochronił rodzinę."
          }
        ]
      },
      {
        "es_word": "protegimos",
        "pl_word": "ochroniliśmy (proteger)",
        "grammar": {
          "tense": "preterite",
          "person": 1,
          "number": "plural"
        },
        "examples": [
          {
            "es_form": "Nosotros [protegimos::ochroniliśmy] a la familia.",
            "pl_translation": "Ochroniliśmy rodzinę."
          }
        ]
      },
      {
        "es_word": "protegisteis",
        "pl_word": "ochroniliście (proteger)",
        "grammar": {
          "tense": "preterite",
          "person": 2,
          "number": "plural"
        },
        "examples": [
          {
            "es_form": "Vosotros [protegisteis::ochroniliście] a la familia.",
            "pl_translation": "Ochroniliście rodzinę."
          }
        ]
      },
      {
        "es_word": "protegieron",
        "pl_word": "ochronili (proteger)",
        "grammar": {
          "tense": "preterite",
          "person": 3,
          "number": "plural"
        },
        "examples": [
          {
            "es_form": "Ellos [protegieron::ochronili] a la familia.",
            "pl_translation": "Ochronili rodzinę."
          }
        ]
      },
      {
        "es_word": "protegeré",
        "pl_word": "będę chronić (proteger)",
        "grammar": {
          "tense": "future",
          "person": 1,
          "number": "singular"
        },
        "examples": [
          {
            "es_form": "Yo [protegeré::będę chronić] a la familia.",
            "pl_translation": "Będę chronić rodzinę."
          }
        ]
      },
      {
        "es_word": "protegerás",
        "pl_word": "będziesz chronić (proteger)",
        "grammar": {
          "tense": "future",
          "person": 2,
          "number": "singular"
        },
        "examples": [
          {
            "es_form": "Tú [protegerás::będziesz chronić] a la familia.",
            "pl_translation": "Będziesz chronić rodzinę."
          }
        ]
      },
      {
        "es_word": "protegerá",
        "pl_word": "będzie chronić (proteger)",
        "grammar": {
          "tense": "future",
          "person": 3,
          "number": "singular"
        },
        "examples": [
          {
            "es_form": "Él [protegerá::będzie chronić] a la familia.",
            "pl_translation": "Będzie chronić rodzinę."
          }
        ]
      },
      {
        "es_word": "protegeremos",
        "pl_word": "będziemy chronić (proteger)",
        "grammar": {
          "tense": "future",
          "person": 1,
          "number": "plural"
        },
        "examples": [
          {
            "es_form": "Nosotros [protegeremos::będziemy chronić] a la familia.",
            "pl_translation": "Będziemy chronić rodzinę."
          }
        ]
      },
      {
        "es_word": "protegeréis",
        "pl_word": "będziecie chronić (proteger)",
        "grammar": {
          "tense": "future",
          "person": 2,
          "number": "plural"
        },
        "examples": [
          {
            "es_form": "Vosotros [protegeréis::będziecie chronić] a la familia.",
            "pl_translation": "Będziecie chronić rodzinę."
          }
        ]
      },
      {
        "es_word": "protegerán",
        "pl_word": "będą chronić (proteger)",
        "grammar": {
          "tense": "future",
          "person": 3,
          "number": "plural"
        },
        "examples": [
          {
            "es_form": "Ellos [protegerán::będą chronić] a la familia.",
            "pl_translation": "Będą chronić rodzinę."
          }
        ]
      }
    ]
  }
]